LimitlessLumos/__init__.py
LimitlessLumos/limitlesslumos.py
LimitlessLumos-1.1.3.dist-info/LICENSE
LimitlessLumos-1.1.3.dist-info/METADATA
LimitlessLumos-1.1.3.dist-info/WHEEL
LimitlessLumos-1.1.3.dist-info/top_level.txt
LimitlessLumos-1.1.3.dist-info/RECORD
