Metadata-Version: 2.2
Name: LimitlessLumos
Version: 1.1.3
Summary: A package providing a Flask-based server to keep Telegram bots and other scripts running indefinitely.
Home-page: https://github.com/TraxDinosaur/LimitlessLumos
Author: TraxDinosaur
Keywords: Flask,Telegram bot,keep alive,web server,threading,LimitlessLumos
Classifier: Programming Language :: Python :: 3
Classifier: License :: OSI Approved
Classifier: Operating System :: OS Independent
Requires-Python: >=3.6
License-File: LICENSE
Requires-Dist: Flask
Dynamic: author
Dynamic: classifier
Dynamic: description
Dynamic: description-content-type
Dynamic: home-page
Dynamic: keywords
Dynamic: requires-dist
Dynamic: requires-python
Dynamic: summary
